primapy_saffron_workflows/__init__.py
primapy_saffron_workflows-0.1.0.dist-info/METADATA
primapy_saffron_workflows-0.1.0.dist-info/WHEEL
primapy_saffron_workflows-0.1.0.dist-info/RECORD
