Metadata-Version: 2.4
Name: primapy-saffron-workflows
Version: 0.1.0
Summary: ML Platform workflows
Requires-Python: >=3.10.13
